[{"id":1,"name":"testproduct 1","desc":"This is testproduct number 1","price":3500,"slug":"testproduct-1","published_at":"2021-02-20T12:08:40.866Z","created_at":"2021-02-20T12:08:30.074Z","updated_at":"2021-02-20T12:08:40.918Z","singleMedia":{"id":1,"name":"samsungGalaxyNote10.png","alternativeText":"","caption":"","width":400,"height":400,"formats":{"thumbnail":{"name":"thumbnail_samsungGalaxyNote10.png","hash":"thumbnail_samsung_Galaxy_Note10_590425b432","ext":".png","mime":"image/png","width":156,"height":156,"size":25.88,"path":null,"url":"/uploads/thumbnail_samsung_Galaxy_Note10_590425b432.png"}},"hash":"samsung_Galaxy_Note10_590425b432","ext":".png","mime":"image/png","size":23.6,"url":"/uploads/samsung_Galaxy_Note10_590425b432.png","previewUrl":null,"provider":"local","provider_metadata":null,"created_at":"2021-02-20T12:07:05.817Z","updated_at":"2021-02-20T12:07:05.834Z"},"multiMedia":[{"id":2,"name":"samsungGalaxyS20.jpg","alternativeText":"","caption":"","width":414,"height":600,"formats":{"thumbnail":{"name":"thumbnail_samsungGalaxyS20.jpg","hash":"thumbnail_samsung_Galaxy_S20_0ece953de1","ext":".jpg","mime":"image/jpeg","width":108,"height":156,"size":4.94,"path":null,"url":"/uploads/thumbnail_samsung_Galaxy_S20_0ece953de1.jpg"},"small":{"name":"small_samsungGalaxyS20.jpg","hash":"small_samsung_Galaxy_S20_0ece953de1","ext":".jpg","mime":"image/jpeg","width":345,"height":500,"size":35.52,"path":null,"url":"/uploads/small_samsung_Galaxy_S20_0ece953de1.jpg"}},"hash":"samsung_Galaxy_S20_0ece953de1","ext":".jpg","mime":"image/jpeg","size":49.18,"url":"/uploads/samsung_Galaxy_S20_0ece953de1.jpg","previewUrl":null,"provider":"local","provider_metadata":null,"created_at":"2021-02-20T12:07:33.072Z","updated_at":"2021-02-20T12:07:33.098Z"},{"id":3,"name":"samsungGalaxyS20Ultra.png","alternativeText":"","caption":"","width":400,"height":400,"formats":{"thumbnail":{"name":"thumbnail_samsungGalaxyS20Ultra.png","hash":"thumbnail_samsung_Galaxy_S20_Ultra_f28f0446b7","ext":".png","mime":"image/png","width":156,"height":156,"size":18.02,"path":null,"url":"/uploads/thumbnail_samsung_Galaxy_S20_Ultra_f28f0446b7.png"}},"hash":"samsung_Galaxy_S20_Ultra_f28f0446b7","ext":".png","mime":"image/png","size":29.7,"url":"/uploads/samsung_Galaxy_S20_Ultra_f28f0446b7.png","previewUrl":null,"provider":"local","provider_metadata":null,"created_at":"2021-02-20T12:07:33.257Z","updated_at":"2021-02-20T12:07:33.287Z"}]},{"id":2,"name":"testproduct 2","desc":"this is testproduct number 2","price":4200,"slug":"testproduct-2","published_at":"2021-02-20T12:10:26.244Z","created_at":"2021-02-20T12:10:21.817Z","updated_at":"2021-02-20T12:10:26.294Z","singleMedia":{"id":4,"name":"iphoneSe2020.png","alternativeText":"","caption":"","width":500,"height":500,"formats":{"thumbnail":{"name":"thumbnail_iphoneSe2020.png","hash":"thumbnail_iphone_Se2020_d60451475d","ext":".png","mime":"image/png","width":156,"height":156,"size":27.9,"path":null,"url":"/uploads/thumbnail_iphone_Se2020_d60451475d.png"}},"hash":"iphone_Se2020_d60451475d","ext":".png","mime":"image/png","size":144.86,"url":"/uploads/iphone_Se2020_d60451475d.png","previewUrl":null,"provider":"local","provider_metadata":null,"created_at":"2021-02-20T12:09:42.578Z","updated_at":"2021-02-20T12:09:42.600Z"},"multiMedia":[{"id":5,"name":"iphone7plus.png","alternativeText":"","caption":"","width":500,"height":500,"formats":{"thumbnail":{"name":"thumbnail_iphone7plus.png","hash":"thumbnail_iphone7plus_d7a0d8ca60","ext":".png","mime":"image/png","width":156,"height":156,"size":22.53,"path":null,"url":"/uploads/thumbnail_iphone7plus_d7a0d8ca60.png"}},"hash":"iphone7plus_d7a0d8ca60","ext":".png","mime":"image/png","size":117.64,"url":"/uploads/iphone7plus_d7a0d8ca60.png","previewUrl":null,"provider":"local","provider_metadata":null,"created_at":"2021-02-20T12:10:14.546Z","updated_at":"2021-02-20T12:10:14.568Z"},{"id":6,"name":"iphoneX.png","alternativeText":"","caption":"","width":320,"height":320,"formats":{"thumbnail":{"name":"thumbnail_iphoneX.png","hash":"thumbnail_iphone_X_1de31bf20a","ext":".png","mime":"image/png","width":156,"height":156,"size":39.97,"path":null,"url":"/uploads/thumbnail_iphone_X_1de31bf20a.png"}},"hash":"iphone_X_1de31bf20a","ext":".png","mime":"image/png","size":85.54,"url":"/uploads/iphone_X_1de31bf20a.png","previewUrl":null,"provider":"local","provider_metadata":null,"created_at":"2021-02-20T12:10:14.882Z","updated_at":"2021-02-20T12:10:14.912Z"},{"id":7,"name":"iphone11proMax.png","alternativeText":"","caption":"","width":400,"height":400,"formats":{"thumbnail":{"name":"thumbnail_iphone11proMax.png","hash":"thumbnail_iphone11pro_Max_9677d12163","ext":".png","mime":"image/png","width":156,"height":156,"size":29.25,"path":null,"url":"/uploads/thumbnail_iphone11pro_Max_9677d12163.png"}},"hash":"iphone11pro_Max_9677d12163","ext":".png","mime":"image/png","size":48.53,"url":"/uploads/iphone11pro_Max_9677d12163.png","previewUrl":null,"provider":"local","provider_metadata":null,"created_at":"2021-02-20T12:10:15.175Z","updated_at":"2021-02-20T12:10:15.199Z"}]}]